Examples/__init__.py
Examples/Algorithms/Main.py
Examples/Algorithms/__init__.py
Examples/Algorithms/Data/__init__.py
Examples/Algorithms/Features/__init__.py
Examples/BIUAutomation/__init__.py
Examples/BIUAutomation/AppTools/__init__.py
Examples/BIUAutomation/Features/__init__.py
Examples/BIUAutomation/Tools/__init__.py
Examples/BackgroundLoadingApp/__init__.py
Examples/BackgroundLoadingApp/Features/__init__.py
Examples/BackgroundLoadingApp/Features/SubFeaturesLoader/Feature2.py
Examples/BackgroundLoadingApp/Features/SubFeaturesLoader/__init__.py
Examples/BackgroundLoadingApp/Features/SubFeaturesLoader/SubFeature2/__init__.py
Examples/BackgroundLoadingApp/UI/__init__.py
Examples/DyClockExample/Main.py
Examples/DyClockExample/__init__.py
Examples/DyClockExample/Features/__init__.py
FTV/__init__.py
FTV/FrameWork/Apps.py
FTV/FrameWork/Features.py
FTV/FrameWork/__init__.py
FTV/Generators/__init__.py
FTV/Generators/GenerateMagicMethods/FileReader.py
FTV/Generators/GenerateMagicMethods/GenerateMagicMethods.py
FTV/Generators/GenerateMagicMethods/__init__.py
FTV/Generators/GenerateMagicMethods/result/MagicMethodsInterfaces.py
FTV/Generators/GenerateMagicMethods/result/__init__.py
FTV/Generators/GenerateMagicMethods/source/Builtins_3_7.py
FTV/Generators/GenerateMagicMethods/source/MagicMethodsInterfacesDemo.py
FTV/Generators/GenerateMagicMethods/source/__init__.py
FTV/Managers/AbstractManager.py
FTV/Managers/ExecutionManager.py
FTV/Managers/FeatureManager.py
FTV/Managers/LogManager.py
FTV/Managers/TriggerManager.py
FTV/Managers/UIManager.py
FTV/Managers/VariableManager.py
FTV/Managers/__init__.py
FTV/Objects/__init__.py
FTV/Objects/Containers/__init__.py
FTV/Objects/Interfaces/__init__.py
FTV/Objects/SystemObjects/DataObject.py
FTV/Objects/SystemObjects/Executions.py
FTV/Objects/SystemObjects/TriggerObjects.py
FTV/Objects/SystemObjects/UIPlatforms.py
FTV/Objects/SystemObjects/__init__.py
FTV/Objects/Variables/AbstractConditions.py
FTV-1.0.9.dist-info/METADATA
FTV-1.0.9.dist-info/WHEEL
FTV-1.0.9.dist-info/top_level.txt
FTV-1.0.9.dist-info/RECORD
