Metadata-Version: 2.1
Name: FTV
Version: 1.0.9
Author: Lahav Svorai
Requires-Dist: wrapt ==1.14.1
